{"hash":"6d1e7dd52e8c17cf4930f349c6afc1a78b2e1c5e","data":{"records":{"id":"Yoga for Kids","title":"Yoga for Kids","belongsTo":{"totalCount":1,"pageInfo":{"totalPages":1,"currentPage":1},"edges":[{"node":{"__typename":"Course","id":"37750dc7-3ef1-11ea-9791-1b580a556b4a","title":"Intro to Yoga Fun for Kids","slug":"intro-to-yoga-fun-for-kids","headline":"Where kids and the young at heart can have fun learning yoga","created":"24th January 2020","tags":[{"title":"Health & Fitness","path":"/tag/Health%20%26%20Fitness/"},{"title":"Yoga","path":"/tag/Yoga/"},{"title":"Yoga for Kids","path":"/tag/Yoga%20for%20Kids/"}]}}]}}},"context":{}}