{"hash":"6d1e7dd52e8c17cf4930f349c6afc1a78b2e1c5e","data":{"records":{"id":"iOS Development","title":"iOS Development","belongsTo":{"totalCount":8,"pageInfo":{"totalPages":1,"currentPage":1},"edges":[{"node":{"__typename":"Course","id":"37749896-3ef1-11ea-9791-1b580a556b4a","title":"How to add In App Purchases to your iPhone app the easy way","slug":"how-to-add-in-app-purchases-to-your-i-phone-app-the-easy-way","headline":"The fastest and easiest way to implement MKStoreKit and boost your sales! Learn how to monetize your app now!","created":"24th January 2020","tags":[{"title":"Development","path":"/tag/Development/"},{"title":"Mobile Apps","path":"/tag/Mobile%20Apps/"},{"title":"iOS Development","path":"/tag/iOS%20Development/"}]}},{"node":{"__typename":"Course","id":"3773d548-3ef1-11ea-9791-1b580a556b4a","title":"Become an iOS Developer from Scratch","slug":"become-an-i-os-developer-from-scratch","headline":"A step-by-step iOS development tutorial for aspiring developers with no coding or Objective-C experience.","created":"24th January 2020","tags":[{"title":"Development","path":"/tag/Development/"},{"title":"Mobile Apps","path":"/tag/Mobile%20Apps/"},{"title":"iOS Development","path":"/tag/iOS%20Development/"}]}},{"node":{"__typename":"Course","id":"37724ea6-3ef1-11ea-9791-1b580a556b4a","title":"This Is How You Make iPhone Apps - iOS Development Course","slug":"this-is-how-you-make-i-phone-apps-i-os-development-course","headline":"Learn every step in iOS App Development with iOS app development tutorial, from creating to submitting to app store.","created":"24th January 2020","tags":[{"title":"Development","path":"/tag/Development/"},{"title":"Mobile Apps","path":"/tag/Mobile%20Apps/"},{"title":"iOS Development","path":"/tag/iOS%20Development/"}]}},{"node":{"__typename":"Course","id":"37722791-3ef1-11ea-9791-1b580a556b4a","title":"iPhone icons gone awesome","slug":"i-phone-icons-gone-awesome","headline":"Learn the fastest, easiest and funnest way of making your iPhone, iPad icons stand out from the crowd","created":"24th January 2020","tags":[{"title":"Design","path":"/tag/Design/"},{"title":"Graphic Design","path":"/tag/Graphic%20Design/"},{"title":"iOS Development","path":"/tag/iOS%20Development/"}]}},{"node":{"__typename":"Course","id":"37722792-3ef1-11ea-9791-1b580a556b4a","title":"Mastering iPhone programming - Lite","slug":"mastering-i-phone-programming-lite","headline":"Quick introduction to iPhone programming with Objective C, Controls in iOS with MVC, Advance Features in iOS with Cocoa","created":"24th January 2020","tags":[{"title":"Development","path":"/tag/Development/"},{"title":"Mobile Apps","path":"/tag/Mobile%20Apps/"},{"title":"iOS Development","path":"/tag/iOS%20Development/"}]}},{"node":{"__typename":"Course","id":"3771d975-3ef1-11ea-9791-1b580a556b4a","title":"Learn to Make iPhone Apps with Objective C for iOS7","slug":"learn-to-make-i-phone-apps-with-objective-c-for-i-o-s7","headline":"Create apps for iOS7 without any programming experience. Learn how to write Objective C code, design UI, and use Xcode.","created":"24th January 2020","tags":[{"title":"Development","path":"/tag/Development/"},{"title":"Mobile Apps","path":"/tag/Mobile%20Apps/"},{"title":"iOS Development","path":"/tag/iOS%20Development/"}]}},{"node":{"__typename":"Course","id":"37716447-3ef1-11ea-9791-1b580a556b4a","title":"Mastering iPhone Programming","slug":"mastering-i-phone-programming","headline":"Complete guide to learn iOS7 iphone Programming with Objective C and Xcode, Cocoa and MVC, Sqlite, OpenGL ES and more.","created":"24th January 2020","tags":[{"title":"Development","path":"/tag/Development/"},{"title":"Mobile Apps","path":"/tag/Mobile%20Apps/"},{"title":"iOS Development","path":"/tag/iOS%20Development/"}]}},{"node":{"__typename":"Course","id":"376afba1-3ef1-11ea-9791-1b580a556b4a","title":"Beginners - How To Create iPhone And iPad Apps - Zero Coding","slug":"beginners-how-to-create-i-phone-and-i-pad-apps-zero-coding","headline":"Learn How To Create IOS Apps And Never Do A Hard Days Work Again - Zero Coding Needed","created":"24th January 2020","tags":[{"title":"Development","path":"/tag/Development/"},{"title":"Mobile Apps","path":"/tag/Mobile%20Apps/"},{"title":"iOS Development","path":"/tag/iOS%20Development/"}]}}]}}},"context":{}}