{"hash":"6d1e7dd52e8c17cf4930f349c6afc1a78b2e1c5e","data":{"records":{"id":"Databases","title":"Databases","belongsTo":{"totalCount":5,"pageInfo":{"totalPages":1,"currentPage":1},"edges":[{"node":{"__typename":"Course","id":"3770ef18-3ef1-11ea-9791-1b580a556b4a","title":"Introduction to SQL Training","slug":"introduction-to-sql-training","headline":"This SQL training course is designed for students new to writing SQL queries. Build applications and generate reports.","created":"24th January 2020","tags":[{"title":"Development","path":"/tag/Development/"},{"title":"Databases","path":"/tag/Databases/"},{"title":"SQL","path":"/tag/SQL/"}]}},{"node":{"__typename":"Course","id":"3770ef12-3ef1-11ea-9791-1b580a556b4a","title":"Beginner's Guide to PostgreSQL","slug":"beginner-s-guide-to-postgre-sql","headline":"PostgreSQL Tutorial: What you need to know to get started with relational databases in PostgreSQL","created":"24th January 2020","tags":[{"title":"Development","path":"/tag/Development/"},{"title":"Databases","path":"/tag/Databases/"},{"title":"PostgreSQL","path":"/tag/PostgreSQL/"}]}},{"node":{"__typename":"Course","id":"37702bc5-3ef1-11ea-9791-1b580a556b4a","title":"Learning MySQL5 - An Easy Way To Master MySQL","slug":"learning-my-sq-l5-an-easy-way-to-master-my-sql","headline":"Learn MySQL 5 With This Hands-On Tutorial Course. Comes Complete With Verifiable Certification of Completion","created":"24th January 2020","tags":[{"title":"Development","path":"/tag/Development/"},{"title":"Databases","path":"/tag/Databases/"},{"title":"MySQL","path":"/tag/MySQL/"}]}},{"node":{"__typename":"Course","id":"376e08e1-3ef1-11ea-9791-1b580a556b4a","title":"Oracle Veritabanı Programlama : SQL, PL/SQL, Oracle Mimarisi","slug":"oracle-veritabani-programlama-sql-pl-sql-oracle-mimarisi","headline":"Türkiye'nin ilk ve en kapsamlı PL/SQL ile Oracle veritabanı programlama eğitimidir.","created":"24th January 2020","tags":[{"title":"Development","path":"/tag/Development/"},{"title":"Databases","path":"/tag/Databases/"},{"title":"Pl/SQL","path":"/tag/Pl%2FSQL/"}]}},{"node":{"__typename":"Course","id":"376ca950-3ef1-11ea-9791-1b580a556b4a","title":"Introduction to Microsoft SQL Server Databases","slug":"introduction-to-microsoft-sql-server-databases","headline":"Learn how to build a simple SQL Server database to collect and analyze your data in this Microsoft SQL server training","created":"24th January 2020","tags":[{"title":"Development","path":"/tag/Development/"},{"title":"Databases","path":"/tag/Databases/"},{"title":"Microsoft SQL","path":"/tag/Microsoft%20SQL/"}]}}]}}},"context":{}}