{"hash":"6d1e7dd52e8c17cf4930f349c6afc1a78b2e1c5e","data":{"records":{"id":"Goal Setting","title":"Goal Setting","belongsTo":{"totalCount":1,"pageInfo":{"totalPages":1,"currentPage":1},"edges":[{"node":{"__typename":"Course","id":"37786929-3ef1-11ea-9791-1b580a556b4a","title":"Smart Goals for a Smart Life","slug":"smart-goals-for-a-smart-life","headline":"Train your brain for success","created":"24th January 2020","tags":[{"title":"Personal Development","path":"/tag/Personal%20Development/"},{"title":"Personal Transformation","path":"/tag/Personal%20Transformation/"},{"title":"Goal Setting","path":"/tag/Goal%20Setting/"}]}}]}}},"context":{}}