{"hash":"6d1e7dd52e8c17cf4930f349c6afc1a78b2e1c5e","data":{"records":{"id":"Investing & Trading","title":"Investing & Trading","belongsTo":{"totalCount":7,"pageInfo":{"totalPages":1,"currentPage":1},"edges":[{"node":{"__typename":"Course","id":"377ab310-3ef1-11ea-9791-1b580a556b4a","title":"Derivatives Trading Course For Beginners Deeply Explained","slug":"derivatives-trading-course-for-beginners-deeply-explained","headline":"The Complete Derivatives Trading Course For Beginners Great For Options/Stock/Commodity/Futures/Currency/Forex Explained","created":"24th January 2020","tags":[{"title":"Finance & Accounting","path":"/tag/Finance%20%26%20Accounting/"},{"title":"Investing & Trading","path":"/tag/Investing%20%26%20Trading/"},{"title":"Derivatives Trading","path":"/tag/Derivatives%20Trading/"}]}},{"node":{"__typename":"Course","id":"37797a91-3ef1-11ea-9791-1b580a556b4a","title":"Morgan教你学习量化投资与程序化交易 (EP7:量化选股:基本面与技术面因子)","slug":"morgan-e-p7","headline":"- Quantitative Investing & Algorithm Trading","created":"24th January 2020","tags":[{"title":"Finance & Accounting","path":"/tag/Finance%20%26%20Accounting/"},{"title":"Investing & Trading","path":"/tag/Investing%20%26%20Trading/"},{"title":"Stock Trading","path":"/tag/Stock%20Trading/"}]}},{"node":{"__typename":"Course","id":"37790564-3ef1-11ea-9791-1b580a556b4a","title":"LONDON ETF ( SAMPLE WATCHLIST - PMI, NMI AND UMCSI Reports )","slug":"london-etf-sample-watchlist-pmi-nmi-and-umcsi-reports","headline":"HOW TO PROFIT UP TO 200% FROM ETF's, WITHOUT TAKING ANY STOCK RISK","created":"24th January 2020","tags":[{"title":"Finance & Accounting","path":"/tag/Finance%20%26%20Accounting/"},{"title":"Investing & Trading","path":"/tag/Investing%20%26%20Trading/"},{"title":"Options Trading","path":"/tag/Options%20Trading/"}]}},{"node":{"__typename":"Course","id":"37789032-3ef1-11ea-9791-1b580a556b4a","title":"TOKYO IRON CONDOR STRATEGY ( IRON CONDOR FOR MONTHLY INCOME)","slug":"tokyo-iron-condor-strategy-iron-condor-for-monthly-income","headline":"HOW TO PROFIT UP TO 34% A MONTH SAFELY WITHOUT SITTING IN FRONT OF A COMPUTER ALL DAY","created":"24th January 2020","tags":[{"title":"Finance & Accounting","path":"/tag/Finance%20%26%20Accounting/"},{"title":"Investing & Trading","path":"/tag/Investing%20%26%20Trading/"},{"title":"Options Trading","path":"/tag/Options%20Trading/"}]}},{"node":{"__typename":"Course","id":"37777ec5-3ef1-11ea-9791-1b580a556b4a","title":"ISTANBUL DIAGONAL/CALENDAR (DOUBLE DIAGONAL-CALENDAR SPREAD)","slug":"istanbul-diagonal-calendar-double-diagonal-calendar-spread","headline":"2020 - HOW TO GET UP TO 145% PROFIT EVERY WEEK WITHOUT TAKING ANY DIRECTIONAL RISK","created":"24th January 2020","tags":[{"title":"Finance & Accounting","path":"/tag/Finance%20%26%20Accounting/"},{"title":"Investing & Trading","path":"/tag/Investing%20%26%20Trading/"},{"title":"Options Trading","path":"/tag/Options%20Trading/"}]}},{"node":{"__typename":"Course","id":"37777ec6-3ef1-11ea-9791-1b580a556b4a","title":"NEW YORK EARNINGS ( POST/PRIOR TRADES-STRADDLE/IRON CONDOR )","slug":"new-york-earnings-post-prior-trades-straddle-iron-condor","headline":"2020 - HOW TO GET THE MOST OUT OF AN EARNINGS EVENT WITHOUT TAKING ANY DIRECTIONAL RISK","created":"24th January 2020","tags":[{"title":"Finance & Accounting","path":"/tag/Finance%20%26%20Accounting/"},{"title":"Investing & Trading","path":"/tag/Investing%20%26%20Trading/"},{"title":"Options Trading","path":"/tag/Options%20Trading/"}]}},{"node":{"__typename":"Course","id":"377757ba-3ef1-11ea-9791-1b580a556b4a","title":"Morgan教你学习量化投资与程序化交易 (EP8:量化择时:打造自己的多空系统)","slug":"morgan-e-p8","headline":"- Quantitative Investing & Algorithm Trading","created":"24th January 2020","tags":[{"title":"Finance & Accounting","path":"/tag/Finance%20%26%20Accounting/"},{"title":"Investing & Trading","path":"/tag/Investing%20%26%20Trading/"},{"title":"Investing","path":"/tag/Investing/"}]}}]}}},"context":{}}